provision/__init__.py
provision/__main__.py
provision/py.typed
provision/cli/__init__.py
provision/cli/main.py
provision/core/__init__.py
provision/core/main.py
provision/core/configs/__init__.py
provision/core/configs/register.py
provision/core/configs/cfg/__init__.py
provision/core/configs/cfg/lightning.py
provision/core/configs/hydra/hydra_logging/rich.yaml
provision/core/configs/hydra/job_logging/rich.yaml
provision/core/experiments/__init__.py
provision/core/experiments/lightning/__init__.py
provision/core/experiments/lightning/experiment.py
provision/core/experiments/lightning/mixins/__init__.py
provision/core/experiments/lightning/mixins/no_train.py
provision/core/experiments/lightning/mixins/wandb.py
provision/core/utils/__init__.py
provision/core/utils/callbacks.py
provision/core/utils/enums.py
provision/core/utils/logging.py
provision/core/utils/metrics.py
provision/core/utils/random.py
provision/core/utils/rundir.py
provision/toolbox/__init__.py
provision/toolbox/models/__init__.py
provision/toolbox/models/convnet.py
provision/toolbox/systems/__init__.py
provision/toolbox/systems/base.py
provision_ai-23.3.24.dist-info/LICENSE
provision_ai-23.3.24.dist-info/METADATA
provision_ai-23.3.24.dist-info/WHEEL
provision_ai-23.3.24.dist-info/entry_points.txt
provision_ai-23.3.24.dist-info/top_level.txt
provision_ai-23.3.24.dist-info/RECORD
